modifinder/__init__.py
modifinder/arguments.py
modifinder/convert.py
modifinder/exceptions.py
modifinder/main.py
modifinder/runner.py
modifinder-1.4.61b0.dist-info/licenses/LICENSE.md
modifinder-1.4.61b0.dist-info/METADATA
modifinder-1.4.61b0.dist-info/WHEEL
modifinder-1.4.61b0.dist-info/top_level.txt
modifinder-1.4.61b0.dist-info/RECORD
