Metadata-Version: 2.4
Name: modifinder
Version: 1.4.61b0
Summary: ModiFinder package
Author-email: Reza Shahneh <mzare008@ucr.edu>
License: ::
Project-URL: Documentation, https://wang-bioinformatics-lab.github.io/ModiFinder_base/
Project-URL: Repository, https://github.com/Wang-Bioinformatics-Lab/ModiFinder_base
Requires-Python: >=3.9
License-File: LICENSE.md
Requires-Dist: cairosvg
Requires-Dist: rdkit
Requires-Dist: requests
Requires-Dist: xlsxwriter
Requires-Dist: prettytable
Requires-Dist: dash
Requires-Dist: numpy
Requires-Dist: tqdm
Requires-Dist: IPython
Requires-Dist: furl
Requires-Dist: pandas
Requires-Dist: dash-bootstrap-components
Requires-Dist: pillow
Requires-Dist: openpyxl
Requires-Dist: openpyxl-image-loader
Requires-Dist: msbuddy==0.2.3
Requires-Dist: seaborn
Requires-Dist: pyteomics
Requires-Dist: matplotlib
Requires-Dist: networkx
Provides-Extra: extras
Dynamic: license-file
